examples/__init__.py
examples/example_00/__init__.py
examples/example_00/example_00.py
examples/example_01/__init__.py
examples/example_01/example_01.py
examples/example_02/__init__.py
examples/example_02/example_02.py
xicsrt/__init__.py
xicsrt/__main__.py
xicsrt/_version.py
xicsrt/xicsrt_config.py
xicsrt/xicsrt_io.py
xicsrt/xicsrt_multiprocessing.py
xicsrt/xicsrt_public.py
xicsrt/xicsrt_raytrace.py
xicsrt/filters/_XicsrtBundleFilter.py
xicsrt/filters/_XicsrtBundleFilterSightline.py
xicsrt/filters/__init__.py
xicsrt/objects/_ConfigObject.py
xicsrt/objects/_Dispatcher.py
xicsrt/objects/_GeometryObject.py
xicsrt/objects/_RayArray.py
xicsrt/objects/__init__.py
xicsrt/optics/_InteractCrystal.py
xicsrt/optics/_InteractMirror.py
xicsrt/optics/_InteractMosaicCrystal.py
xicsrt/optics/_InteractNone.py
xicsrt/optics/_InteractObject.py
xicsrt/optics/_ShapeCylinder.py
xicsrt/optics/_ShapeMesh.py
xicsrt/optics/_ShapeMeshCylinder.py
xicsrt/optics/_ShapeMeshSphere.py
xicsrt/optics/_ShapeMeshTorus.py
xicsrt/optics/_ShapeObject.py
xicsrt/optics/_ShapePlane.py
xicsrt/optics/_ShapeSphere.py
xicsrt/optics/_ShapeTorus.py
xicsrt/optics/_TraceObject.py
xicsrt/optics/_XicsrtOpticAperture.py
xicsrt/optics/_XicsrtOpticCylindricalCrystal.py
xicsrt/optics/_XicsrtOpticDetector.py
xicsrt/optics/_XicsrtOpticMeshCrystal.py
xicsrt/optics/_XicsrtOpticMeshCylindricalCrystal.py
xicsrt/optics/_XicsrtOpticMeshMirror.py
xicsrt/optics/_XicsrtOpticMeshMosaicCrystal.py
xicsrt/optics/_XicsrtOpticMeshSphericalCrystal.py
xicsrt/optics/_XicsrtOpticMeshToroidalCrystal.py
xicsrt/optics/_XicsrtOpticPlanarCrystal.py
xicsrt/optics/_XicsrtOpticPlanarMirror.py
xicsrt/optics/_XicsrtOpticPlanarMosaicCrystal.py
xicsrt/optics/_XicsrtOpticSphericalCrystal.py
xicsrt/optics/_XicsrtOpticSphericalMirror.py
xicsrt/optics/_XicsrtOpticSphericalMosaicCrystal.py
xicsrt/optics/_XicsrtOpticToroidalCrystal.py
xicsrt/optics/__init__.py
xicsrt/sources/_XicsrtPlasmaCubic.py
xicsrt/sources/_XicsrtPlasmaCylindrical.py
xicsrt-0.8.13.dist-info/AUTHORS
xicsrt-0.8.13.dist-info/LICENSE
xicsrt-0.8.13.dist-info/METADATA
xicsrt-0.8.13.dist-info/WHEEL
xicsrt-0.8.13.dist-info/entry_points.txt
xicsrt-0.8.13.dist-info/top_level.txt
xicsrt-0.8.13.dist-info/RECORD
