Metadata-Version: 2.1
Name: xicsrt
Version: 0.8.13
Summary: A photon based raytracing application written in Python.
Home-page: https://github.com/PrincetonUniversity/xicsrt
Author: Novimir Antoniuk Pablant
Author-email: npablant@pppl.gov
Maintainer: Novimir Antoniuk Pablant
Maintainer-email: npablant@pppl.gov
License: MIT
Classifier: Development Status :: 4 - Beta
Classifier: License :: OSI Approved :: MIT License
Classifier: Programming Language :: Python :: 3
Classifier: Operating System :: OS Independent
Requires-Python: >=3.8
License-File: LICENSE
License-File: AUTHORS
Requires-Dist: numpy
Requires-Dist: scipy
Requires-Dist: pillow
Requires-Dist: h5py
